methodcrm_client/__init__.py
methodcrm_client/api_client.py
methodcrm_client/configuration.py
methodcrm_client/exceptions.py
methodcrm_client/rest.py
methodcrm_client/api/__init__.py
methodcrm_client/api/api_key_api.py
methodcrm_client/api/files_api.py
methodcrm_client/api/me_api.py
methodcrm_client/api/tables_api.py
methodcrm_client/models/__init__.py
methodcrm_client/models/file_link.py
methodcrm_client/models/file_metadata.py
methodcrm_client/models/inline_object.py
methodcrm_client/models/problem_details.py
methodcrm_client/models/query_records_result.py
methodcrm_client/models/validation_problem_details.py
methodcrm_client-0.0.2.dist-info/METADATA
methodcrm_client-0.0.2.dist-info/WHEEL
methodcrm_client-0.0.2.dist-info/top_level.txt
methodcrm_client-0.0.2.dist-info/RECORD
